transformerslocal/model_cards/README.md
transformerslocal/scripts/benchmark/trainer-benchmark.py
transformerslocal/scripts/check_tokenizers.py
transformerslocal/scripts/distributed/torch-distributed-gpu-test.py
transformerslocal/scripts/fsmt/convert-allenai-wmt16.sh
transformerslocal/scripts/fsmt/convert-allenai-wmt19.sh
transformerslocal/scripts/fsmt/convert-facebook-wmt19.sh
transformerslocal/scripts/fsmt/eval-allenai-wmt16.sh
transformerslocal/scripts/fsmt/eval-allenai-wmt19.sh
transformerslocal/scripts/fsmt/eval-facebook-wmt19.sh
transformerslocal/scripts/fsmt/fsmt-make-super-tiny-model.py
transformerslocal/scripts/fsmt/fsmt-make-tiny-model.py
transformerslocal/scripts/fsmt/gen-card-allenai-wmt16.py
transformerslocal/scripts/fsmt/gen-card-allenai-wmt19.py
transformerslocal/scripts/fsmt/gen-card-facebook-wmt19.py
transformerslocal/scripts/fsmt/s3-move.sh
transformerslocal/scripts/fsmt/tests-to-run.sh
transformerslocal/scripts/pegasus/build_test_sample_spm_no_bos.py
transformerslocal/scripts/stale.py
transformerslocal/scripts/tatoeba/README.md
transformerslocal/scripts/tatoeba/upload_models.sh
transformerslocal/setup.py
transformerslocal/src/transformers/__init__.py
transformerslocal/src/transformers/activations.py
transformerslocal/src/transformers/activations_tf.py
transformerslocal/src/transformers/audio_utils.py
transformerslocal/src/transformers/benchmark/__init__.py
transformerslocal/src/transformers/benchmark/benchmark.py
transformerslocal/src/transformers/benchmark/benchmark_args.py
transformerslocal/src/transformers/benchmark/benchmark_args_tf.py
transformerslocal/src/transformers/benchmark/benchmark_args_utils.py
transformerslocal/src/transformers/benchmark/benchmark_tf.py
transformerslocal/src/transformers/benchmark/benchmark_utils.py
transformerslocal/src/transformers/commands/__init__.py
transformerslocal/src/transformers/commands/add_new_model.py
transformerslocal/src/transformers/commands/add_new_model_like.py
transformerslocal-0.0.4.dist-info/METADATA
transformerslocal-0.0.4.dist-info/WHEEL
transformerslocal-0.0.4.dist-info/RECORD
