Metadata-Version: 2.1
Name: transformerslocal
Version: 0.0.4
Summary: Parameter-Efficient Fine-Tuning Enhances Adaptation of Single Cell Large Language Model.
Home-page: https://github.com/BeacherKim/scPEFT_reproduction
License: MIT
Author: Fei He
Requires-Python: >=3.7.12,<3.11
Classifier: License :: OSI Approved :: MIT License
Classifier: Programming Language :: Python :: 3
Classifier: Programming Language :: Python :: 3.8
Classifier: Programming Language :: Python :: 3.9
Classifier: Programming Language :: Python :: 3.10
Requires-Dist: torch (>=1.13.0)
Requires-Dist: torchtext
Project-URL: Repository, https://github.com/BeacherKim/scPEFT_reproduction
